[
  {
    "_meta": "temporada_activa",
    "valor": 2025
  },
  {
    "temporada": 2026,
    "posicion": 1,
    "jugador": "Abel",
    "pj": 40,
    "pg": 21,
    "pp": 19,
    "dif_p": 2,
    "cg": 181,
    "cp": 179,
    "dif_c": 2,
    "puntos": 286
  },
  {
    "temporada": 2026,
    "posicion": 2,
    "jugador": "Batto",
    "pj": 40,
    "pg": 21,
    "pp": 19,
    "dif_p": 2,
    "cg": 181,
    "cp": 179,
    "dif_c": 2,
    "puntos": 286
  },
  {
    "temporada": 2026,
    "posicion": 3,
    "jugador": "Carutox",
    "pj": 40,
    "pg": 21,
    "pp": 19,
    "dif_p": 2,
    "cg": 181,
    "cp": 179,
    "dif_c": 2,
    "puntos": 286
  },
  {
    "temporada": 2026,
    "posicion": 4,
    "jugador": "Darkslain",
    "pj": 40,
    "pg": 21,
    "pp": 19,
    "dif_p": 2,
    "cg": 181,
    "cp": 179,
    "dif_c": 2,
    "puntos": 286
  },
  {
    "temporada": 2026,
    "posicion": 5,
    "jugador": "Espartaco",
    "pj": 40,
    "pg": 21,
    "pp": 19,
    "dif_p": 2,
    "cg": 181,
    "cp": 179,
    "dif_c": 2,
    "puntos": 286
  },
  {
    "temporada": 2026,
    "posicion": 6,
    "jugador": "Graptopetalo",
    "pj": 40,
    "pg": 21,
    "pp": 19,
    "dif_p": 2,
    "cg": 181,
    "cp": 179,
    "dif_c": 2,
    "puntos": 286
  },
  {
    "temporada": 2026,
    "posicion": 7,
    "jugador": "Juanmanova",
    "pj": 40,
    "pg": 21,
    "pp": 19,
    "dif_p": 2,
    "cg": 181,
    "cp": 179,
    "dif_c": 2,
    "puntos": 286
  },
  {
    "temporada": 2026,
    "posicion": 8,
    "jugador": "Kokkyo",
    "pj": 40,
    "pg": 21,
    "pp": 19,
    "dif_p": 2,
    "cg": 181,
    "cp": 179,
    "dif_c": 2,
    "puntos": 286
  },
  {
    "temporada": 2026,
    "posicion": 9,
    "jugador": "Lokiyo",
    "pj": 40,
    "pg": 21,
    "pp": 19,
    "dif_p": 2,
    "cg": 181,
    "cp": 179,
    "dif_c": 2,
    "puntos": 286
  },
  {
    "temporada": 2026,
    "posicion": 10,
    "jugador": "Marcade",
    "pj": 40,
    "pg": 21,
    "pp": 19,
    "dif_p": 2,
    "cg": 181,
    "cp": 179,
    "dif_c": 2,
    "puntos": 286
  },
  {
    "temporada": 2026,
    "posicion": 11,
    "jugador": "Marshall",
    "pj": 40,
    "pg": 21,
    "pp": 19,
    "dif_p": 2,
    "cg": 181,
    "cp": 179,
    "dif_c": 2,
    "puntos": 286
  },
  {
    "temporada": 2026,
    "posicion": 12,
    "jugador": "Mintxarra",
    "pj": 40,
    "pg": 21,
    "pp": 19,
    "dif_p": 2,
    "cg": 181,
    "cp": 179,
    "dif_c": 2,
    "puntos": 286
  },
  {
    "temporada": 2026,
    "posicion": 13,
    "jugador": "Only",
    "pj": 40,
    "pg": 21,
    "pp": 19,
    "dif_p": 2,
    "cg": 181,
    "cp": 179,
    "dif_c": 2,
    "puntos": 286
  },
  {
    "temporada": 2026,
    "posicion": 14,
    "jugador": "Patata Navidenya",
    "pj": 40,
    "pg": 21,
    "pp": 19,
    "dif_p": 2,
    "cg": 181,
    "cp": 179,
    "dif_c": 2,
    "puntos": 286
  },
  {
    "temporada": 2026,
    "posicion": 15,
    "jugador": "Pof",
    "pj": 40,
    "pg": 21,
    "pp": 19,
    "dif_p": 2,
    "cg": 181,
    "cp": 179,
    "dif_c": 2,
    "puntos": 286
  },
  {
    "temporada": 2026,
    "posicion": 16,
    "jugador": "Ricky",
    "pj": 40,
    "pg": 21,
    "pp": 19,
    "dif_p": 2,
    "cg": 181,
    "cp": 179,
    "dif_c": 2,
    "puntos": 286
  },
  {
    "temporada": 2026,
    "posicion": 17,
    "jugador": "Roger Scroll",
    "pj": 40,
    "pg": 21,
    "pp": 19,
    "dif_p": 2,
    "cg": 181,
    "cp": 179,
    "dif_c": 2,
    "puntos": 286
  },
  {
    "temporada": 2026,
    "posicion": 18,
    "jugador": "Sf77",
    "pj": 40,
    "pg": 21,
    "pp": 19,
    "dif_p": 2,
    "cg": 181,
    "cp": 179,
    "dif_c": 2,
    "puntos": 286
  },
  {
    "temporada": 2026,
    "posicion": 19,
    "jugador": "Tifus",
    "pj": 40,
    "pg": 21,
    "pp": 19,
    "dif_p": 2,
    "cg": 181,
    "cp": 179,
    "dif_c": 2,
    "puntos": 286
  },
  {
    "temporada": 2026,
    "posicion": 20,
    "jugador": "Vins",
    "pj": 40,
    "pg": 21,
    "pp": 19,
    "dif_p": 2,
    "cg": 181,
    "cp": 179,
    "dif_c": 2,
    "puntos": 286
  },
  {
    "temporada": 2026,
    "posicion": 21,
    "jugador": "RedSpecial",
    "pj": 40,
    "pg": 20,
    "pp": 20,
    "dif_p": 0,
    "cg": 180,
    "cp": 180,
    "dif_c": 0,
    "puntos": 280
  },
  {
    "temporada": 2026,
    "posicion": 22,
    "jugador": "Yonpol",
    "pj": 40,
    "pg": 20,
    "pp": 20,
    "dif_p": 0,
    "cg": 180,
    "cp": 180,
    "dif_c": 0,
    "puntos": 280
  },
  {
    "temporada": 2026,
    "posicion": 23,
    "jugador": "AL",
    "pj": 40,
    "pg": 19,
    "pp": 21,
    "dif_p": -2,
    "cg": 179,
    "cp": 181,
    "dif_c": -2,
    "puntos": 274
  },
  {
    "temporada": 2026,
    "posicion": 24,
    "jugador": "alexdms92",
    "pj": 40,
    "pg": 19,
    "pp": 21,
    "dif_p": -2,
    "cg": 179,
    "cp": 181,
    "dif_c": -2,
    "puntos": 274
  },
  {
    "temporada": 2026,
    "posicion": 25,
    "jugador": "Boni",
    "pj": 40,
    "pg": 19,
    "pp": 21,
    "dif_p": -2,
    "cg": 179,
    "cp": 181,
    "dif_c": -2,
    "puntos": 274
  },
  {
    "temporada": 2026,
    "posicion": 26,
    "jugador": "Carlescot",
    "pj": 40,
    "pg": 19,
    "pp": 21,
    "dif_p": -2,
    "cg": 179,
    "cp": 181,
    "dif_c": -2,
    "puntos": 274
  },
  {
    "temporada": 2026,
    "posicion": 27,
    "jugador": "Edgar",
    "pj": 40,
    "pg": 19,
    "pp": 21,
    "dif_p": -2,
    "cg": 179,
    "cp": 181,
    "dif_c": -2,
    "puntos": 274
  },
  {
    "temporada": 2026,
    "posicion": 28,
    "jugador": "Goiko",
    "pj": 40,
    "pg": 19,
    "pp": 21,
    "dif_p": -2,
    "cg": 179,
    "cp": 181,
    "dif_c": -2,
    "puntos": 274
  },
  {
    "temporada": 2026,
    "posicion": 29,
    "jugador": "John McClane",
    "pj": 40,
    "pg": 19,
    "pp": 21,
    "dif_p": -2,
    "cg": 179,
    "cp": 181,
    "dif_c": -2,
    "puntos": 274
  },
  {
    "temporada": 2026,
    "posicion": 30,
    "jugador": "Kepasaco",
    "pj": 40,
    "pg": 19,
    "pp": 21,
    "dif_p": -2,
    "cg": 179,
    "cp": 181,
    "dif_c": -2,
    "puntos": 274
  },
  {
    "temporada": 2026,
    "posicion": 31,
    "jugador": "Kinof",
    "pj": 40,
    "pg": 19,
    "pp": 21,
    "dif_p": -2,
    "cg": 179,
    "cp": 181,
    "dif_c": -2,
    "puntos": 274
  },
  {
    "temporada": 2026,
    "posicion": 32,
    "jugador": "Lars",
    "pj": 40,
    "pg": 19,
    "pp": 21,
    "dif_p": -2,
    "cg": 179,
    "cp": 181,
    "dif_c": -2,
    "puntos": 274
  },
  {
    "temporada": 2026,
    "posicion": 33,
    "jugador": "Lukas",
    "pj": 40,
    "pg": 19,
    "pp": 21,
    "dif_p": -2,
    "cg": 179,
    "cp": 181,
    "dif_c": -2,
    "puntos": 274
  },
  {
    "temporada": 2026,
    "posicion": 34,
    "jugador": "Matatoros",
    "pj": 40,
    "pg": 19,
    "pp": 21,
    "dif_p": -2,
    "cg": 179,
    "cp": 181,
    "dif_c": -2,
    "puntos": 274
  },
  {
    "temporada": 2026,
    "posicion": 35,
    "jugador": "Pablotarus",
    "pj": 40,
    "pg": 19,
    "pp": 21,
    "dif_p": -2,
    "cg": 179,
    "cp": 181,
    "dif_c": -2,
    "puntos": 274
  },
  {
    "temporada": 2026,
    "posicion": 36,
    "jugador": "Pep Juan",
    "pj": 40,
    "pg": 19,
    "pp": 21,
    "dif_p": -2,
    "cg": 179,
    "cp": 181,
    "dif_c": -2,
    "puntos": 274
  },
  {
    "temporada": 2026,
    "posicion": 37,
    "jugador": "Saulon",
    "pj": 40,
    "pg": 19,
    "pp": 21,
    "dif_p": -2,
    "cg": 179,
    "cp": 181,
    "dif_c": -2,
    "puntos": 274
  },
  {
    "temporada": 2026,
    "posicion": 38,
    "jugador": "Sepia",
    "pj": 40,
    "pg": 19,
    "pp": 21,
    "dif_p": -2,
    "cg": 179,
    "cp": 181,
    "dif_c": -2,
    "puntos": 274
  },
  {
    "temporada": 2026,
    "posicion": 39,
    "jugador": "Sheriff",
    "pj": 40,
    "pg": 19,
    "pp": 21,
    "dif_p": -2,
    "cg": 179,
    "cp": 181,
    "dif_c": -2,
    "puntos": 274
  },
  {
    "temporada": 2026,
    "posicion": 40,
    "jugador": "Siddi",
    "pj": 40,
    "pg": 19,
    "pp": 21,
    "dif_p": -2,
    "cg": 179,
    "cp": 181,
    "dif_c": -2,
    "puntos": 274
  },
  {
    "temporada": 2026,
    "posicion": 41,
    "jugador": "Tonichan",
    "pj": 40,
    "pg": 19,
    "pp": 21,
    "dif_p": -2,
    "cg": 179,
    "cp": 181,
    "dif_c": -2,
    "puntos": 274
  },
  {
    "temporada": 2026,
    "posicion": 42,
    "jugador": "Yogaboy",
    "pj": 40,
    "pg": 19,
    "pp": 21,
    "dif_p": -2,
    "cg": 179,
    "cp": 181,
    "dif_c": -2,
    "puntos": 274
  },
  {
    "temporada": 2025,
    "posicion": 1,
    "jugador": "alexdms92",
    "pj": 0,
    "pg": 0,
    "pp": 0,
    "dif_p": 0,
    "cg": 0,
    "cp": 0,
    "dif_c": 0,
    "puntos": 0
  },
  {
    "temporada": 2025,
    "posicion": 2,
    "jugador": "Carutox",
    "pj": 0,
    "pg": 0,
    "pp": 0,
    "dif_p": 0,
    "cg": 0,
    "cp": 0,
    "dif_c": 0,
    "puntos": 0
  },
  {
    "temporada": 2025,
    "posicion": 3,
    "jugador": "Darkslain",
    "pj": 0,
    "pg": 0,
    "pp": 0,
    "dif_p": 0,
    "cg": 0,
    "cp": 0,
    "dif_c": 0,
    "puntos": 0
  },
  {
    "temporada": 2025,
    "posicion": 4,
    "jugador": "John McClane",
    "pj": 0,
    "pg": 0,
    "pp": 0,
    "dif_p": 0,
    "cg": 0,
    "cp": 0,
    "dif_c": 0,
    "puntos": 0
  },
  {
    "temporada": 2025,
    "posicion": 5,
    "jugador": "Kepasaco",
    "pj": 0,
    "pg": 0,
    "pp": 0,
    "dif_p": 0,
    "cg": 0,
    "cp": 0,
    "dif_c": 0,
    "puntos": 0
  },
  {
    "temporada": 2025,
    "posicion": 6,
    "jugador": "Kinof",
    "pj": 0,
    "pg": 0,
    "pp": 0,
    "dif_p": 0,
    "cg": 0,
    "cp": 0,
    "dif_c": 0,
    "puntos": 0
  },
  {
    "temporada": 2025,
    "posicion": 7,
    "jugador": "Kokkyo",
    "pj": 0,
    "pg": 0,
    "pp": 0,
    "dif_p": 0,
    "cg": 0,
    "cp": 0,
    "dif_c": 0,
    "puntos": 0
  },
  {
    "temporada": 2025,
    "posicion": 8,
    "jugador": "Lokiyo",
    "pj": 0,
    "pg": 0,
    "pp": 0,
    "dif_p": 0,
    "cg": 0,
    "cp": 0,
    "dif_c": 0,
    "puntos": 0
  },
  {
    "temporada": 2025,
    "posicion": 9,
    "jugador": "Lukas",
    "pj": 0,
    "pg": 0,
    "pp": 0,
    "dif_p": 0,
    "cg": 0,
    "cp": 0,
    "dif_c": 0,
    "puntos": 0
  },
  {
    "temporada": 2025,
    "posicion": 10,
    "jugador": "Marcade",
    "pj": 0,
    "pg": 0,
    "pp": 0,
    "dif_p": 0,
    "cg": 0,
    "cp": 0,
    "dif_c": 0,
    "puntos": 0
  },
  {
    "temporada": 2025,
    "posicion": 11,
    "jugador": "Matatoros",
    "pj": 0,
    "pg": 0,
    "pp": 0,
    "dif_p": 0,
    "cg": 0,
    "cp": 0,
    "dif_c": 0,
    "puntos": 0
  },
  {
    "temporada": 2025,
    "posicion": 12,
    "jugador": "Only",
    "pj": 0,
    "pg": 0,
    "pp": 0,
    "dif_p": 0,
    "cg": 0,
    "cp": 0,
    "dif_c": 0,
    "puntos": 0
  },
  {
    "temporada": 2025,
    "posicion": 13,
    "jugador": "Pablotarus",
    "pj": 0,
    "pg": 0,
    "pp": 0,
    "dif_p": 0,
    "cg": 0,
    "cp": 0,
    "dif_c": 0,
    "puntos": 0
  },
  {
    "temporada": 2025,
    "posicion": 14,
    "jugador": "Pof",
    "pj": 0,
    "pg": 0,
    "pp": 0,
    "dif_p": 0,
    "cg": 0,
    "cp": 0,
    "dif_c": 0,
    "puntos": 0
  },
  {
    "temporada": 2025,
    "posicion": 15,
    "jugador": "RedSpecial",
    "pj": 0,
    "pg": 0,
    "pp": 0,
    "dif_p": 0,
    "cg": 0,
    "cp": 0,
    "dif_c": 0,
    "puntos": 0
  },
  {
    "temporada": 2025,
    "posicion": 16,
    "jugador": "Ricky",
    "pj": 0,
    "pg": 0,
    "pp": 0,
    "dif_p": 0,
    "cg": 0,
    "cp": 0,
    "dif_c": 0,
    "puntos": 0
  },
  {
    "temporada": 2025,
    "posicion": 17,
    "jugador": "Sf77",
    "pj": 0,
    "pg": 0,
    "pp": 0,
    "dif_p": 0,
    "cg": 0,
    "cp": 0,
    "dif_c": 0,
    "puntos": 0
  },
  {
    "temporada": 2025,
    "posicion": 18,
    "jugador": "Sheriff",
    "pj": 0,
    "pg": 0,
    "pp": 0,
    "dif_p": 0,
    "cg": 0,
    "cp": 0,
    "dif_c": 0,
    "puntos": 0
  },
  {
    "temporada": 2025,
    "posicion": 19,
    "jugador": "Siddi",
    "pj": 0,
    "pg": 0,
    "pp": 0,
    "dif_p": 0,
    "cg": 0,
    "cp": 0,
    "dif_c": 0,
    "puntos": 0
  },
  {
    "temporada": 2025,
    "posicion": 20,
    "jugador": "Vins",
    "pj": 0,
    "pg": 0,
    "pp": 0,
    "dif_p": 0,
    "cg": 0,
    "cp": 0,
    "dif_c": 0,
    "puntos": 0
  }
]
